LICENSE
README.rst
setup.py
exotic_ld/__init__.py
exotic_ld/ld_computation.py
exotic_ld/ld_grids.py
exotic_ld/ld_laws.py
exotic_ld/ld_requests.py
exotic_ld.egg-info/PKG-INFO
exotic_ld.egg-info/SOURCES.txt
exotic_ld.egg-info/dependency_links.txt
exotic_ld.egg-info/requires.txt
exotic_ld.egg-info/top_level.txt
exotic_ld.egg-info/zip-safe
grid_build/kd_trees/__init__.py
grid_build/kd_trees/kurucz_tree.pickle
grid_build/kd_trees/mps1_tree.pickle
grid_build/kd_trees/mps2_tree.pickle
grid_build/kd_trees/phoenix_tree.pickle
grid_build/kd_trees/stagger_tree.pickle